<?xml version="1.0" encoding="UTF-8"?>
<job-scheduling-data xmlns="http://www.quartz-scheduler.org/xml/JobSchedulingData"
                     xmlns:xsi="http://www.w3.org/2001/XMLSchema-instance"
                     xsi:schemaLocation="
                     http://www.quartz-scheduler.org/xml/JobSchedulingData
                     http://www.quartz-scheduler.org/xml/job_scheduling_data_1_8.xsd"
                     version="1.8">

    <schedule>
        <job>
            <name>ScanDirectory</name>
            <group>jobDetail-group</group>

            <description>ScanDirectory from tomcat conf</description>
            <job-class>net.individuals.quartz.ScanDirectoryJob</job-class>
            <job-data-map>
                <entry>
                    <key>SCAN_DIR</key>
                    <value>\apache-tomcat-7.0.39\conf</value>
                </entry>
            </job-data-map>
        </job>

        <trigger>
            <simple>
                <name>scanTrigger</name>
                <group>trigger-group</group>

                <!--jobName和jobGroup必须与对应的Job匹配-->
                <job-name>ScanDirectory</job-name>
                <job-group>jobDetail-group</job-group>

                <!--注意日期和时间+08:00 表示东八区-->
                <start-time>2008-09-03T14:43:00+08:00</start-time>
                <!-- repeat indefinitely every 10 seconds -->
                <repeat-count>-1</repeat-count>
                <repeat-interval>10000</repeat-interval>
            </simple>
        </trigger>
    </schedule>
</job-scheduling-data>